nonebot_plugin_api_scheduler/__init__.py
nonebot_plugin_api_scheduler-1.1.2.dist-info/LICENSE
nonebot_plugin_api_scheduler-1.1.2.dist-info/METADATA
nonebot_plugin_api_scheduler-1.1.2.dist-info/WHEEL
nonebot_plugin_api_scheduler-1.1.2.dist-info/RECORD
