Metadata-Version: 2.1
Name: nonebot-plugin-api-scheduler
Version: 1.1.2
Summary: 像操作API一样设置定时任务&计划任务
Home-page: https://github.com/mmdexb/nonebot-plugin-api-scheduler/
License:  GPL-3.0 license
Keywords: nonebot,nonebot2,scheduler
Author: mmdexb
Requires-Python: >=3.9,<4.0
Classifier: License :: Other/Proprietary License
Classifier: Programming Language :: Python :: 3
Classifier: Programming Language :: Python :: 3.9
Classifier: Programming Language :: Python :: 3.10
Classifier: Programming Language :: Python :: 3.11
Classifier: Programming Language :: Python :: 3.12
Classifier: Programming Language :: Python :: 3.13
Requires-Dist: apscheduler (>=3.7.0,<4.0.0)
Requires-Dist: fastapi (>=0.115.2,<0.116.0)
Requires-Dist: nonebot-adapter-onebot (>=2.4.0)
Requires-Dist: nonebot-plugin-apscheduler (>=0.5.0,<0.6.0)
Requires-Dist: nonebot2 (>=2.1.1,<3.0.0)
Requires-Dist: pydantic (>=2.8.0)
Project-URL: Repository, https://github.com/mmdexb/nonebot-plugin-api-scheduler/
